Metadata-Version: 2.1
Name: freesourceai
Version: 0.5
Summary: FreeSourceAI(FreeGPT) - ChatGPT but without prompt.API By:MubiLop
Author: FreeGPT
Author-email: Ruslan German <projectsruslans@gmail.com>
Classifier: Programming Language :: Python :: 3
Classifier: License :: OSI Approved :: MIT License
Classifier: Operating System :: OS Independent
Requires-Python: >=3.8
License-File: LICENSE
